cqh_util/__init__.py
cqh_util/ansible_util.py
cqh_util/argparser_util.py
cqh_util/city_and_loc_util.py
cqh_util/city_util.py
cqh_util/common_util.py
cqh_util/conf.py
cqh_util/escape_util.py
cqh_util/honcho_util.py
cqh_util/image_util.py
cqh_util/invoke_util.py
cqh_util/jinja2_util.py
cqh_util/logger_util.py
cqh_util/mixin.py
cqh_util/mod_util.py
cqh_util/progress_util.py
cqh_util/request_util.py
cqh_util-0.1.26.dist-info/METADATA
cqh_util-0.1.26.dist-info/WHEEL
cqh_util-0.1.26.dist-info/entry_points.txt
cqh_util-0.1.26.dist-info/top_level.txt
cqh_util-0.1.26.dist-info/RECORD
