Metadata-Version: 2.1
Name: cqh-util
Version: 0.1.26
Summary: cqh utils function
Home-page: https://github.com/chen19901225/cqh_util
Author: chenqinghe
Author-email: 1832866299@qq.com
Classifier: Programming Language :: Python :: 3
Classifier: License :: OSI Approved :: MIT License
Classifier: Operating System :: Unix
Requires-Python: >=3.6
Requires-Dist: gitpython
Requires-Dist: jinja2
Requires-Dist: honcho
